openmc_geometry_plot/He4.h5
openmc_geometry_plot/__init__.py
openmc_geometry_plot/_version.py
openmc_geometry_plot/app.py
openmc_geometry_plot/core.py
openmc_geometry_plot/cross_sections.xml
openmc_geometry_plot/launch.py
openmc_geometry_plot-0.5.0.dist-info/METADATA
openmc_geometry_plot-0.5.0.dist-info/WHEEL
openmc_geometry_plot-0.5.0.dist-info/entry_points.txt
openmc_geometry_plot-0.5.0.dist-info/top_level.txt
openmc_geometry_plot-0.5.0.dist-info/RECORD
