Metadata-Version: 2.4
Name: openmc_geometry_plot
Version: 0.5.0
Summary: Plot OpenMC geometry, interactive or static 2D slice plots.
Author-email: Jonathan Shimwell <mail@jshimwell.com>
Project-URL: Homepage, https://github.com/fusion-energy/openmc_geometry_plot
Project-URL: Bug Tracker, https://github.com/fusion-energy/openmc_geometry_plot/issues
Keywords: openmc,geometry,plot,slice
Classifier: Programming Language :: Python :: 3
Classifier: License :: OSI Approved :: MIT License
Classifier: Operating System :: OS Independent
Requires-Python: >=3.8
Requires-Dist: numpy>=1.21.1
Requires-Dist: streamlit
Requires-Dist: plotly
Requires-Dist: matplotlib
Provides-Extra: tests
Requires-Dist: pytest; extra == "tests"
